baker_cli/__init__.py
baker_cli/__main__.py
baker_cli/cli.py
baker_cli/core.py
baker_cli/templates/README.md
baker_cli/templates/build-settings.yml
baker_cli/templates/pyproject.toml
baker_cli/templates/ci/github-actions.yml.j2
baker_cli/templates/docker/base/Dockerfile
baker_cli/templates/docker/dev/Dockerfile
baker_cli/templates/docker/release/Dockerfile
baker_cli-1.0.5.dist-info/licenses/LICENSE
baker_cli-1.0.5.dist-info/METADATA
baker_cli-1.0.5.dist-info/WHEEL
baker_cli-1.0.5.dist-info/entry_points.txt
baker_cli-1.0.5.dist-info/top_level.txt
baker_cli-1.0.5.dist-info/RECORD
