Metadata-Version: 2.4
Name: baker-cli
Version: 1.0.5
Summary: Super simple Docker Build Dependency Pipeline
Author-email: Team IQ <service@get-iq.com>
License: MIT
Project-URL: Homepage, https://github.com/iq-company/baker-cli
Requires-Python: >=3.8
License-File: LICENSE
Requires-Dist: PyYAML>=6.0
Requires-Dist: typer>=0.12.0
Requires-Dist: Jinja2>=3.1
Dynamic: license-file
